pz_rail-1.2.3.dist-info/licenses/LICENSE
rail/hub/__init__.py
rail/hub/_version.py
pz_rail-1.2.3.dist-info/METADATA
pz_rail-1.2.3.dist-info/WHEEL
pz_rail-1.2.3.dist-info/top_level.txt
pz_rail-1.2.3.dist-info/RECORD
