Metadata-Version: 2.4
Name: pz-rail
Version: 1.2.3
Author-email: "LSST Dark Energy Science Collaboration (DESC)" <later@later.com>
License: MIT License
Classifier: Development Status :: 4 - Beta
Classifier: License :: OSI Approved :: MIT License
Classifier: Intended Audience :: Developers
Classifier: Intended Audience :: Science/Research
Classifier: Operating System :: OS Independent
Classifier: Programming Language :: Python
Requires-Python: >=3.9
License-File: LICENSE
Requires-Dist: pz-rail-base
Provides-Extra: algos
Requires-Dist: pz-rail-astro-tools; extra == "algos"
Requires-Dist: pz-rail-bpz; extra == "algos"
Requires-Dist: pz-rail-cmnn; extra == "algos"
Requires-Dist: pz-rail-dnf; extra == "algos"
Requires-Dist: pz-rail-dsps; extra == "algos"
Requires-Dist: pz-rail-flexzboost; extra == "algos"
Requires-Dist: pz-rail-fsps; extra == "algos"
Requires-Dist: pz-rail-gpz-v1; extra == "algos"
Requires-Dist: pz-rail-pzflow; extra == "algos"
Requires-Dist: pz-rail-sklearn; extra == "algos"
Requires-Dist: pz-rail-som; extra == "algos"
Requires-Dist: pz-rail-yaw; extra == "algos"
Requires-Dist: pz-rail-lephare; extra == "algos"
Requires-Dist: qp-prob[full]>=1.0.0; extra == "algos"
Provides-Extra: nb
Requires-Dist: pz-rail[algos]; extra == "nb"
Requires-Dist: jupyter; extra == "nb"
Requires-Dist: seaborn; extra == "nb"
Provides-Extra: dev
Requires-Dist: pz-rail[algos]; extra == "dev"
Requires-Dist: jupyter; extra == "dev"
Requires-Dist: seaborn; extra == "dev"
Requires-Dist: corner; extra == "dev"
Requires-Dist: pandas; extra == "dev"
Requires-Dist: h5py; extra == "dev"
Requires-Dist: matplotlib; extra == "dev"
Requires-Dist: coverage; extra == "dev"
Requires-Dist: pytest; extra == "dev"
Requires-Dist: pytest-cov; extra == "dev"
Requires-Dist: pre-commit; extra == "dev"
Requires-Dist: pylint; extra == "dev"
Provides-Extra: docs
Requires-Dist: nbsphinx; extra == "docs"
Requires-Dist: sphinx==6.1.3; extra == "docs"
Requires-Dist: sphinx-autodoc-typehints; extra == "docs"
Requires-Dist: sphinx_rtd_theme==1.2.0; extra == "docs"
Requires-Dist: sphinx-autoapi==2.0.1; extra == "docs"
Requires-Dist: sphinx-tabs; extra == "docs"
Requires-Dist: sphinx-click; extra == "docs"
Dynamic: license-file
